{
  "IsRegenerate": true,
  "MenuPosition": "main",
  "RelativeNamespace": "WithdrawalOrders",
  "EntityName": "WithdrawalOrder",
  "EntityNamePlural": "WithdrawalOrders",
  "TableName": "WithdrawalOrders",
  "PrimaryKeyType": "long",
  "BaseClass": "FullAuditedEntity",
  "EntityHistory": false,
  "AutoMigration": true,
  "UpdateDatabase": true,
  "CreateUserInterface": true,
  "CreateViewOnly": true,
  "CreateExcelExport": true,
  "IsNonModalCRUDPage": false,
  "IsMasterDetailPage": false,
  "GenerateOverridableEntity": false,
  "GenerateUnitTest": false,
  "GenerateUiTest": false,
  "PagePermission": {
    "Host": false,
    "Tenant": false
  },
  "Properties": [
    {
      "Name": "MerchantCode",
      "Type": "string",
      "MaxLength": 50,
      "MinLength": 1,
      "Range": {
        "IsRangeSet": false,
        "MinimumValue": 0.0,
        "MaximumValue": 0.0
      },
      "Required": false,
      "Nullable": false,
      "Regex": "",
      "IsMultiLingual": false,
      "UserInterface": {
        "AdvancedFilter": true,
        "List": true,
        "CreateOrUpdate": true
      },
      "ViewType": null,
      "AdditionalData": {}
    },
    {
      "Name": "MerchantId",
      "Type": "int",
      "MaxLength": -1,
      "MinLength": -1,
      "Range": {
        "IsRangeSet": false,
        "MinimumValue": 0.0,
        "MaximumValue": 0.0
      },
      "Required": false,
      "Nullable": false,
      "Regex": "",
      "IsMultiLingual": false,
      "UserInterface": {
        "AdvancedFilter": false,
        "List": false,
        "CreateOrUpdate": false
      },
      "ViewType": null,
      "AdditionalData": {}
    },
    {
      "Name": "PlatformCode",
      "Type": "string",
      "MaxLength": 50,
      "MinLength": 1,
      "Range": {
        "IsRangeSet": false,
        "MinimumValue": 0.0,
        "MaximumValue": 0.0
      },
      "Required": false,
      "Nullable": false,
      "Regex": "",
      "IsMultiLingual": false,
      "UserInterface": {
        "AdvancedFilter": false,
        "List": false,
        "CreateOrUpdate": false
      },
      "ViewType": null,
      "AdditionalData": {}
    },
    {
      "Name": "WithdrawNo",
      "Type": "string",
      "MaxLength": 50,
      "MinLength": 1,
      "Range": {
        "IsRangeSet": false,
        "MinimumValue": 0.0,
        "MaximumValue": 0.0
      },
      "Required": false,
      "Nullable": false,
      "Regex": "",
      "IsMultiLingual": false,
      "UserInterface": {
        "AdvancedFilter": false,
        "List": false,
        "CreateOrUpdate": false
      },
      "ViewType": null,
      "AdditionalData": {}
    },
    {
      "Name": "OrderStatus",
      "Type": "WithdrawalOrderStatusEnum",
      "MaxLength": -1,
      "MinLength": -1,
      "Range": {
        "IsRangeSet": false,
        "MinimumValue": 0.0,
        "MaximumValue": 0.0
      },
      "Required": false,
      "Nullable": false,
      "Regex": "",
      "IsMultiLingual": false,
      "UserInterface": {
        "AdvancedFilter": false,
        "List": false,
        "CreateOrUpdate": false
      },
      "ViewType": null,
      "AdditionalData": {}
    },
    {
      "Name": "OrderMoney",
      "Type": "decimal",
      "MaxLength": -1,
      "MinLength": -1,
      "Range": {
        "IsRangeSet": false,
        "MinimumValue": 0.0,
        "MaximumValue": 0.0
      },
      "Required": false,
      "Nullable": false,
      "Regex": "",
      "IsMultiLingual": false,
      "UserInterface": {
        "AdvancedFilter": false,
        "List": false,
        "CreateOrUpdate": false
      },
      "ViewType": null,
      "AdditionalData": {}
    },
    {
      "Name": "Rate",
      "Type": "decimal",
      "MaxLength": -1,
      "MinLength": -1,
      "Range": {
        "IsRangeSet": false,
        "MinimumValue": 0.0,
        "MaximumValue": 0.0
      },
      "Required": false,
      "Nullable": false,
      "Regex": "",
      "IsMultiLingual": false,
      "UserInterface": {
        "AdvancedFilter": false,
        "List": false,
        "CreateOrUpdate": false
      },
      "ViewType": null,
      "AdditionalData": {}
    },
    {
      "Name": "FeeMoney",
      "Type": "decimal",
      "MaxLength": -1,
      "MinLength": -1,
      "Range": {
        "IsRangeSet": false,
        "MinimumValue": 0.0,
        "MaximumValue": 0.0
      },
      "Required": false,
      "Nullable": false,
      "Regex": "",
      "IsMultiLingual": false,
      "UserInterface": {
        "AdvancedFilter": false,
        "List": false,
        "CreateOrUpdate": false
      },
      "ViewType": null,
      "AdditionalData": {}
    },
    {
      "Name": "TransactionNo",
      "Type": "string",
      "MaxLength": 50,
      "MinLength": 1,
      "Range": {
        "IsRangeSet": false,
        "MinimumValue": 0.0,
        "MaximumValue": 0.0
      },
      "Required": false,
      "Nullable": false,
      "Regex": "",
      "IsMultiLingual": false,
      "UserInterface": {
        "AdvancedFilter": true,
        "List": false,
        "CreateOrUpdate": false
      },
      "ViewType": null,
      "AdditionalData": {}
    },
    {
      "Name": "TransactionTime",
      "Type": "DateTime",
      "MaxLength": -1,
      "MinLength": -1,
      "Range": {
        "IsRangeSet": false,
        "MinimumValue": 0.0,
        "MaximumValue": 0.0
      },
      "Required": false,
      "Nullable": false,
      "Regex": "",
      "IsMultiLingual": false,
      "UserInterface": {
        "AdvancedFilter": false,
        "List": false,
        "CreateOrUpdate": false
      },
      "ViewType": null,
      "AdditionalData": {}
    },
    {
      "Name": "BenAccountName",
      "Type": "string",
      "MaxLength": 50,
      "MinLength": 1,
      "Range": {
        "IsRangeSet": false,
        "MinimumValue": 0.0,
        "MaximumValue": 0.0
      },
      "Required": false,
      "Nullable": false,
      "Regex": "",
      "IsMultiLingual": false,
      "UserInterface": {
        "AdvancedFilter": true,
        "List": false,
        "CreateOrUpdate": false
      },
      "ViewType": null,
      "AdditionalData": {}
    },
    {
      "Name": "BenAccountNo",
      "Type": "string",
      "MaxLength": 50,
      "MinLength": 1,
      "Range": {
        "IsRangeSet": false,
        "MinimumValue": 0.0,
        "MaximumValue": 0.0
      },
      "Required": false,
      "Nullable": false,
      "Regex": "",
      "IsMultiLingual": false,
      "UserInterface": {
        "AdvancedFilter": true,
        "List": false,
        "CreateOrUpdate": false
      },
      "ViewType": null,
      "AdditionalData": {}
    },
    {
      "Name": "BenBankName",
      "Type": "string",
      "MaxLength": 50,
      "MinLength": 1,
      "Range": {
        "IsRangeSet": false,
        "MinimumValue": 0.0,
        "MaximumValue": 0.0
      },
      "Required": false,
      "Nullable": false,
      "Regex": "",
      "IsMultiLingual": false,
      "UserInterface": {
        "AdvancedFilter": true,
        "List": false,
        "CreateOrUpdate": false
      },
      "ViewType": null,
      "AdditionalData": {}
    },
    {
      "Name": "NotifyUrl",
      "Type": "string",
      "MaxLength": 200,
      "MinLength": 1,
      "Range": {
        "IsRangeSet": false,
        "MinimumValue": 0.0,
        "MaximumValue": 0.0
      },
      "Required": false,
      "Nullable": false,
      "Regex": "",
      "IsMultiLingual": false,
      "UserInterface": {
        "AdvancedFilter": false,
        "List": false,
        "CreateOrUpdate": false
      },
      "ViewType": null,
      "AdditionalData": {}
    },
    {
      "Name": "OrderNumber",
      "Type": "string",
      "MaxLength": 50,
      "MinLength": 1,
      "Range": {
        "IsRangeSet": false,
        "MinimumValue": 0.0,
        "MaximumValue": 0.0
      },
      "Required": false,
      "Nullable": false,
      "Regex": "",
      "IsMultiLingual": false,
      "UserInterface": {
        "AdvancedFilter": true,
        "List": false,
        "CreateOrUpdate": false
      },
      "ViewType": null,
      "AdditionalData": {}
    },
    {
      "Name": "ReceiptUrl",
      "Type": "string",
      "MaxLength": 200,
      "MinLength": 1,
      "Range": {
        "IsRangeSet": false,
        "MinimumValue": 0.0,
        "MaximumValue": 0.0
      },
      "Required": false,
      "Nullable": false,
      "Regex": "",
      "IsMultiLingual": false,
      "UserInterface": {
        "AdvancedFilter": false,
        "List": false,
        "CreateOrUpdate": false
      },
      "ViewType": null,
      "AdditionalData": {}
    },
    {
      "Name": "DeviceId",
      "Type": "int",
      "MaxLength": -1,
      "MinLength": -1,
      "Range": {
        "IsRangeSet": false,
        "MinimumValue": 0.0,
        "MaximumValue": 0.0
      },
      "Required": false,
      "Nullable": false,
      "Regex": "",
      "IsMultiLingual": false,
      "UserInterface": {
        "AdvancedFilter": false,
        "List": false,
        "CreateOrUpdate": false
      },
      "ViewType": null,
      "AdditionalData": {}
    },
    {
      "Name": "OrderType",
      "Type": "WithdrawalOrderTypeEnum",
      "MaxLength": -1,
      "MinLength": -1,
      "Range": {
        "IsRangeSet": false,
        "MinimumValue": 0.0,
        "MaximumValue": 0.0
      },
      "Required": false,
      "Nullable": false,
      "Regex": "",
      "IsMultiLingual": false,
      "UserInterface": {
        "AdvancedFilter": false,
        "List": false,
        "CreateOrUpdate": false
      },
      "ViewType": null,
      "AdditionalData": {}
    },
    {
      "Name": "NotifyStatus",
      "Type": "WithdrawalNotifyStatusEnum",
      "MaxLength": -1,
      "MinLength": -1,
      "Range": {
        "IsRangeSet": false,
        "MinimumValue": 0.0,
        "MaximumValue": 0.0
      },
      "Required": false,
      "Nullable": false,
      "Regex": "",
      "IsMultiLingual": false,
      "UserInterface": {
        "AdvancedFilter": false,
        "List": false,
        "CreateOrUpdate": false
      },
      "ViewType": null,
      "AdditionalData": {}
    },
    {
      "Name": "NotifyNumber",
      "Type": "int",
      "MaxLength": -1,
      "MinLength": -1,
      "Range": {
        "IsRangeSet": false,
        "MinimumValue": 0.0,
        "MaximumValue": 0.0
      },
      "Required": false,
      "Nullable": false,
      "Regex": "",
      "IsMultiLingual": false,
      "UserInterface": {
        "AdvancedFilter": false,
        "List": false,
        "CreateOrUpdate": false
      },
      "ViewType": null,
      "AdditionalData": {}
    },
    {
      "Name": "Description",
      "Type": "string",
      "MaxLength": 3000,
      "MinLength": 1,
      "Range": {
        "IsRangeSet": false,
        "MinimumValue": 0.0,
        "MaximumValue": 0.0
      },
      "Required": false,
      "Nullable": false,
      "Regex": "",
      "IsMultiLingual": false,
      "UserInterface": {
        "AdvancedFilter": false,
        "List": false,
        "CreateOrUpdate": false
      },
      "ViewType": null,
      "AdditionalData": {}
    },
    {
      "Name": "Remark",
      "Type": "string",
      "MaxLength": 5000,
      "MinLength": 1,
      "Range": {
        "IsRangeSet": false,
        "MinimumValue": 0.0,
        "MaximumValue": 0.0
      },
      "Required": false,
      "Nullable": false,
      "Regex": "",
      "IsMultiLingual": false,
      "UserInterface": {
        "AdvancedFilter": false,
        "List": false,
        "CreateOrUpdate": false
      },
      "ViewType": null,
      "AdditionalData": {}
    },
    {
      "Name": "CreationTime",
      "Type": "DateTime",
      "MaxLength": -1,
      "MinLength": -1,
      "Range": {
        "IsRangeSet": false,
        "MinimumValue": 0.0,
        "MaximumValue": 0.0
      },
      "Required": false,
      "Nullable": false,
      "Regex": "",
      "IsMultiLingual": false,
      "UserInterface": {
        "AdvancedFilter": false,
        "List": false,
        "CreateOrUpdate": false
      },
      "ViewType": null,
      "AdditionalData": {}
    },
    {
      "Name": "CreationUnixTime",
      "Type": "long",
      "MaxLength": -1,
      "MinLength": -1,
      "Range": {
        "IsRangeSet": false,
        "MinimumValue": 0.0,
        "MaximumValue": 0.0
      },
      "Required": false,
      "Nullable": false,
      "Regex": "",
      "IsMultiLingual": false,
      "UserInterface": {
        "AdvancedFilter": false,
        "List": false,
        "CreateOrUpdate": false
      },
      "ViewType": null,
      "AdditionalData": {}
    }
  ],
  "NavigationProperties": [],
  "NavigationPropertyOneToManyTables": [],
  "EnumDefinitions": [
    {
      "Name": "WithdrawalOrderStatusEnum",
      "Namespace": "Neptune.NsPay.WithdrawalOrders",
      "EnumProperties": [
        {
          "Name": "Wait",
          "Value": 0
        },
        {
          "Name": "Pending",
          "Value": 1
        },
        {
          "Name": "Success",
          "Value": 2
        },
        {
          "Name": "Fail",
          "Value": 3
        },
        {
          "Name": "ErrorCard",
          "Value": 4
        },
        {
          "Name": "ErrorBank",
          "Value": 5
        },
        {
          "Name": "TimeOut",
          "Value": 6
        },
        {
          "Name": "Cancel",
          "Value": 7
        }
      ]
    },
    {
      "Name": "WithdrawalOrderTypeEnum",
      "Namespace": "Neptune.NsPay.WithdrawalOrders",
      "EnumProperties": [
        {
          "Name": "Inside",
          "Value": 0
        },
        {
          "Name": "Outside",
          "Value": 1
        }
      ]
    },
    {
      "Name": "WithdrawalNotifyStatusEnum",
      "Namespace": "Neptune.NsPay.WithdrawalOrders",
      "EnumProperties": [
        {
          "Name": "Wait",
          "Value": 0
        },
        {
          "Name": "Success",
          "Value": 1
        },
        {
          "Name": "Fail",
          "Value": 2
        },
        {
          "Name": "ManualProcessing",
          "Value": 3
        }
      ]
    }
  ],
  "DbContext": null
}